routing_lib/__init__.py
routing_lib/routing_algorithms.py
routing_lib/routing_measures.py
routing_lib/routing_utils.py
routing_lib-0.2.3.dist-info/LICENSE
routing_lib-0.2.3.dist-info/METADATA
routing_lib-0.2.3.dist-info/WHEEL
routing_lib-0.2.3.dist-info/top_level.txt
routing_lib-0.2.3.dist-info/RECORD
