Metadata-Version: 2.1
Name: routing-lib
Version: 0.2.3
Summary: Small package with alternative routing algorithms and measures.
Home-page: https://github.com/lwdovico/routing-lib
Author: Ludovico Lemma
Author-email: lwdovico@protonmail.com
License: MIT
Keywords: Utils
License-File: LICENSE
Requires-Dist: matplotlib
Requires-Dist: numpy
Requires-Dist: Shapely ==1.8.5
Requires-Dist: Fiona
Requires-Dist: rtree
Requires-Dist: pyproj
Requires-Dist: pygeos
Requires-Dist: scikit-mobility
Requires-Dist: geopandas
Requires-Dist: compress-json
Requires-Dist: tqdm
Requires-Dist: igraph
Requires-Dist: eclipse-sumo ==1.15.0
Requires-Dist: sumolib ==1.15.0
Requires-Dist: libsumo ==1.15.0
Requires-Dist: seaborn
